tensorflow_gcs_config/__init__.py
tensorflow_gcs_config/_gcs_config_ops.so
tensorflow_gcs_config-2.16.1.data/data/_gcs_config_ops.so/_gcs_config_ops.so
tensorflow_gcs_config-2.16.1.dist-info/METADATA
tensorflow_gcs_config-2.16.1.dist-info/WHEEL
tensorflow_gcs_config-2.16.1.dist-info/top_level.txt
tensorflow_gcs_config-2.16.1.dist-info/RECORD
