Metadata-Version: 2.1
Name: tensorflow-gcs-config
Version: 2.16.1
Summary: TensorFlow operations for configuring access to GCS (Google Compute Storage) resources.
Author: Google, Inc.
